spellatron/__init__.py
spellatron/__main__.py
spellatron/applications.py
spellatron/checker.py
spellatron/handlers.py
spellatron/data/data.txt
spellatron-0.0.5.dist-info/WHEEL
spellatron-0.0.5.dist-info/METADATA
spellatron-0.0.5.dist-info/RECORD
