Metadata-Version: 1.2
Name: spellatron
Version: 0.0.5
Summary: Web version of spellchecker based on http://norvig.com/spell-correct.html 
Home-page: https://github.com/jnosal/spellatron
License: UNKNOWN
Author: Jacek Nosal
Author-email: jacek.nosal@outlook.com
Classifier: License :: OSI Approved :: MIT License
Requires-Dist: tornado (>=4.0)
